Workbook
Name BtfeIndexSheetTable: #REF!
Name IQ_CH: 110000
Name IQ_CQ: 5000
Name IQ_CY: 10000
Name IQ_DAILY: 500000
Name IQ_FH: 100000
Name IQ_FQ: 500
Name IQ_FY: 1000
Name IQ_LTM: 2000
Name IQ_MONTH: 15000
Name IQ_NTM: 6000
Name IQ_WEEK: 50000
Name IQ_YTD: 3000

Sheet Sheet1
A1: PDF | B1: Company | C1: Theme | D1: Definition | E1: Extracted Commentary | F1: Match/No-match | G1: Similarity Score | H1: Commentary
A2: C:\Users\73335\OneDrive - Bain\Desktop\FS-ECR-repo\fs-earnings_call_reader\src\notebooks\submission_to_fs_6thAug\FS PDFs\American International Group Inc._Earnings Call_2023-05-05_English.pdf | B2: American International Group Inc. | C2: Macro factors | D2: Tag a commentary under the Macro Factors theme if it includes any reference—explicit or implicit—to the broader macroeconomic environment or external systemic influences affecting business performance. This includes mentions of economic slowdown, recession, uncertainty, market cycles, credit losses, or challenging operating conditions. Tag if the discussion involves monetary indicators such as inflation, interest rates (domestic or foreign), discount rates, investment yields, credit spreads, or currency and foreign exchange impacts. Also include insurance and financial-specific macro drivers such as mortality experience (including seasonal or pandemic-related surges), expected credit losses (ECL), movements in insurance liabilities, or gains/losses tied to market conditions. Furthermore, tag content that refers to external shocks like pandemics (e.g. COVID-19), natural disasters (e.g. hurricanes, floods), or geopolitical disruptions. Additionally, include discussions that indirectly reflect macro context—such as tough environments, changes in investor sentiment, demand volatility, or strategic repositioning in response to macro trends—even if specific macro terms are not used. | E2: 1. We continue to make meaningful progress across AIG and achieve important milestones, even in the face of ongoing complexity in the insurance industry, volatile market conditions and general economic uncertainty. | F2: {=_xldudf_BOARDFLARE_FMATCH(E2,'FS Consolidated Comments'!C$76:C$137,0.13)} -> #VALUE! | G2: {=_FV(F2,"Similarity")} -> 0 | H2: {=_FV(F2,"Match")}
A3: C:\Users\73335\OneDrive - Bain\Desktop\FS-ECR-repo\fs-earnings_call_reader\src\notebooks\submission_to_fs_6thAug\FS PDFs\American International Group Inc._Earnings Call_2023-05-05_English.pdf | B3: American International Group Inc. | C3: Macro factors | D3: Tag a commentary under the Macro Factors theme if it includes any reference—explicit or implicit—to the broader macroeconomic environment or external systemic influences affecting business performance. This includes mentions of economic slowdown, recession, uncertainty, market cycles, credit losses, or challenging operating conditions. Tag if the discussion involves monetary indicators such as inflation, interest rates (domestic or foreign), discount rates, investment yields, credit spreads, or currency and foreign exchange impacts. Also include insurance and financial-specific macro drivers such as mortality experience (including seasonal or pandemic-related surges), expected credit losses (ECL), movements in insurance liabilities, or gains/losses tied to market conditions. Furthermore, tag content that refers to external shocks like pandemics (e.g. COVID-19), natural disasters (e.g. hurricanes, floods), or geopolitical disruptions. Additionally, include discussions that indirectly reflect macro context—such as tough environments, changes in investor sentiment, demand volatility, or strategic repositioning in response to macro trends—even if specific macro terms are not used. | E3: 2. During the first quarter, we were prepared to launch a secondary offering of Corebridge common stock, but chose not to proceed when equity markets became volatile due to issues in the financial sector. | F3: {=_xldudf_BOARDFLARE_FMATCH(E3,'FS Consolidated Comments'!C$76:C$137,0.13)} -> #VALUE! | G3: {=_FV(F3,"Similarity")} -> 0 | H3: {=_FV(F3,"Match")}
A4: C:\Users\73335\OneDrive - Bain\Desktop\FS-ECR-repo\fs-earnings_call_reader\src\notebooks\submission_to_fs_6thAug\FS PDFs\American International Group Inc._Earnings Call_2023-05-05_English.pdf | B4: American International Group Inc. | C4: Macro factors | D4: Tag a commentary under the Macro Factors theme if it includes any reference—explicit or implicit—to the broader macroeconomic environment or external systemic influences affecting business performance. This includes mentions of economic slowdown, recession, uncertainty, market cycles, credit losses, or challenging operating conditions. Tag if the discussion involves monetary indicators such as inflation, interest rates (domestic or foreign), discount rates, investment yields, credit spreads, or currency and foreign exchange impacts. Also include insurance and financial-specific macro drivers such as mortality experience (including seasonal or pandemic-related surges), expected credit losses (ECL), movements in insurance liabilities, or gains/losses tied to market conditions. Furthermore, tag content that refers to external shocks like pandemics (e.g. COVID-19), natural disasters (e.g. hurricanes, floods), or geopolitical disruptions. Additionally, include discussions that indirectly reflect macro context—such as tough environments, changes in investor sentiment, demand volatility, or strategic repositioning in response to macro trends—even if specific macro terms are not used. | E4: 3. Shifting back to our $15 \%$ net premiums written growth in the first quarter, this result was impressive despite the headwinds we continue to see in Financial Lines, where overall net premiums written contracted 9\% due to increased competition putting pressure on pricing as well as continued slowdown in M\&A and other transactional business. | F4: {=_xldudf_BOARDFLARE_FMATCH(E4,'FS Consolidated Comments'!C$76:C$137,0.13)} -> #VALUE! | G4: {=_FV(F4,"Similarity")} -> 0.21 | H4: {=_FV(F4,"Match")} -> where overall net premiums written contracted 9% due to increased competition putting pressure on pricing as well as continued slowdown in M&A and other transactional business.
A5: C:\Users\73335\OneDrive - Bain\Desktop\FS-ECR-repo\fs-earnings_call_reader\src\notebooks\submission_to_fs_6thAug\FS PDFs\American International Group Inc._Earnings Call_2023-05-05_English.pdf | B5: American International Group Inc. | C5: Macro factors | D5: Tag a commentary under the Macro Factors theme if it includes any reference—explicit or implicit—to the broader macroeconomic environment or external systemic influences affecting business performance. This includes mentions of economic slowdown, recession, uncertainty, market cycles, credit losses, or challenging operating conditions. Tag if the discussion involves monetary indicators such as inflation, interest rates (domestic or foreign), discount rates, investment yields, credit spreads, or currency and foreign exchange impacts. Also include insurance and financial-specific macro drivers such as mortality experience (including seasonal or pandemic-related surges), expected credit losses (ECL), movements in insurance liabilities, or gains/losses tied to market conditions. Furthermore, tag content that refers to external shocks like pandemics (e.g. COVID-19), natural disasters (e.g. hurricanes, floods), or geopolitical disruptions. Additionally, include discussions that indirectly reflect macro context—such as tough environments, changes in investor sentiment, demand volatility, or strategic repositioning in response to macro trends—even if specific macro terms are not used. | E5: 4. Turning to capital management. The first quarter marked another quarter of continued progress and execution of our balanced strategy. In addition to the first quarter share repurchases and dividends that I mentioned earlier, against the backdrop of an unstable macroeconomic environment, we thought it was prudent to raise $\$ 750$ million of debt at the end of March. | F5: {=_xldudf_BOARDFLARE_FMATCH(E5,'FS Consolidated Comments'!C$76:C$137,0.13)} -> #VALUE! | G5: {=_FV(F5,"Similarity")} -> 0.22 | H5: {=_FV(F5,"Match")} -> In addition to the first quarter share repurchases and dividends that I mentioned earlier, against the backdrop of an unstable macroeconomic environment, we thought it was prudent to raise $750 million of debt at the end of March.
A6: C:\Users\73335\OneDrive - Bain\Desktop\FS-ECR-repo\fs-earnings_call_reader\src\notebooks\submission_to_fs_6thAug\FS PDFs\American International Group Inc._Earnings Call_2023-05-05_English.pdf | B6: American International Group Inc. | C6: Macro factors | D6: Tag a commentary under the Macro Factors theme if it includes any reference—explicit or implicit—to the broader macroeconomic environment or external systemic influences affecting business performance. This includes mentions of economic slowdown, recession, uncertainty, market cycles, credit losses, or challenging operating conditions. Tag if the discussion involves monetary indicators such as inflation, interest rates (domestic or foreign), discount rates, investment yields, credit spreads, or currency and foreign exchange impacts. Also include insurance and financial-specific macro drivers such as mortality experience (including seasonal or pandemic-related surges), expected credit losses (ECL), movements in insurance liabilities, or gains/losses tied to market conditions. Furthermore, tag content that refers to external shocks like pandemics (e.g. COVID-19), natural disasters (e.g. hurricanes, floods), or geopolitical disruptions. Additionally, include discussions that indirectly reflect macro context—such as tough environments, changes in investor sentiment, demand volatility, or strategic repositioning in response to macro trends—even if specific macro terms are not used. | E6: 5. As Peter noted, L\&R premiums and deposits were very strong at $\$ 10.4$ billion. Notably, Individual Retirement sales were $\$ 4.9$ billion, a $26 \%$ increase over the prior year quarter with record levels of fixed and fixed index annuity sales because of higher crediting rates. | F6: {=_xldudf_BOARDFLARE_FMATCH(E6,'FS Consolidated Comments'!C$76:C$137,0.13)} -> #VALUE! | G6: {=_FV(F6,"Similarity")} -> 0 | H6: {=_FV(F6,"Match")}
A7: C:\Users\73335\OneDrive - Bain\Desktop\FS-ECR-repo\fs-earnings_call_reader\src\notebooks\submission_to_fs_6thAug\FS PDFs\American International Group Inc._Earnings Call_2023-05-05_English.pdf | B7: American International Group Inc. | C7: Macro factors | D7: Tag a commentary under the Macro Factors theme if it includes any reference—explicit or implicit—to the broader macroeconomic environment or external systemic influences affecting business performance. This includes mentions of economic slowdown, recession, uncertainty, market cycles, credit losses, or challenging operating conditions. Tag if the discussion involves monetary indicators such as inflation, interest rates (domestic or foreign), discount rates, investment yields, credit spreads, or currency and foreign exchange impacts. Also include insurance and financial-specific macro drivers such as mortality experience (including seasonal or pandemic-related surges), expected credit losses (ECL), movements in insurance liabilities, or gains/losses tied to market conditions. Furthermore, tag content that refers to external shocks like pandemics (e.g. COVID-19), natural disasters (e.g. hurricanes, floods), or geopolitical disruptions. Additionally, include discussions that indirectly reflect macro context—such as tough environments, changes in investor sentiment, demand volatility, or strategic repositioning in response to macro trends—even if specific macro terms are not used. | E7: 6. Income on fixed maturities and loans rose by $\$ 573$ million over the prior year, with average new money reinvestment rates of $5.35 \%$, about 220 basis points above sales and maturities. | F7: {=_xldudf_BOARDFLARE_FMATCH(E7,'FS Consolidated Comments'!C$76:C$137,0.13)} -> #VALUE! | G7: {=_FV(F7,"Similarity")} -> 0 | H7: {=_FV(F7,"Match")}
A8: C:\Users\73335\OneDrive - Bain\Desktop\FS-ECR-repo\fs-earnings_call_reader\src\notebooks\submission_to_fs_6thAug\FS PDFs\American International Group Inc._Earnings Call_2023-05-05_English.pdf | B8: American International Group Inc. | C8: Macro factors | D8: Tag a commentary under the Macro Factors theme if it includes any reference—explicit or implicit—to the broader macroeconomic environment or external systemic influences affecting business performance. This includes mentions of economic slowdown, recession, uncertainty, market cycles, credit losses, or challenging operating conditions. Tag if the discussion involves monetary indicators such as inflation, interest rates (domestic or foreign), discount rates, investment yields, credit spreads, or currency and foreign exchange impacts. Also include insurance and financial-specific macro drivers such as mortality experience (including seasonal or pandemic-related surges), expected credit losses (ECL), movements in insurance liabilities, or gains/losses tied to market conditions. Furthermore, tag content that refers to external shocks like pandemics (e.g. COVID-19), natural disasters (e.g. hurricanes, floods), or geopolitical disruptions. Additionally, include discussions that indirectly reflect macro context—such as tough environments, changes in investor sentiment, demand volatility, or strategic repositioning in response to macro trends—even if specific macro terms are not used. | E8: 7. Book value per common share was $\$ 58.87$ at quarter end, up $7 \%$ from year-end, principally due to higher valuations on available-for-sale securities due to lower long-term interest rates. | F8: {=_xldudf_BOARDFLARE_FMATCH(E8,'FS Consolidated Comments'!C$76:C$137,0.13)} -> #VALUE! | G8: {=_FV(F8,"Similarity")} -> 0.13 | H8: {=_FV(F8,"Match")} -> So higher interest rates have slowed the amortization on certain VFA contracts.
A9: C:\Users\73335\OneDrive - Bain\Desktop\FS-ECR-repo\fs-earnings_call_reader\src\notebooks\submission_to_fs_6thAug\FS PDFs\American International Group Inc._Earnings Call_2023-05-05_English.pdf | B9: American International Group Inc. | C9: Macro factors | D9: Tag a commentary under the Macro Factors theme if it includes any reference—explicit or implicit—to the broader macroeconomic environment or external systemic influences affecting business performance. This includes mentions of economic slowdown, recession, uncertainty, market cycles, credit losses, or challenging operating conditions. Tag if the discussion involves monetary indicators such as inflation, interest rates (domestic or foreign), discount rates, investment yields, credit spreads, or currency and foreign exchange impacts. Also include insurance and financial-specific macro drivers such as mortality experience (including seasonal or pandemic-related surges), expected credit losses (ECL), movements in insurance liabilities, or gains/losses tied to market conditions. Furthermore, tag content that refers to external shocks like pandemics (e.g. COVID-19), natural disasters (e.g. hurricanes, floods), or geopolitical disruptions. Additionally, include discussions that indirectly reflect macro context—such as tough environments, changes in investor sentiment, demand volatility, or strategic repositioning in response to macro trends—even if specific macro terms are not used. | E9: 8. Our leverage ratio declined to $32.8 \%$, down about 1 point from year-end even with the new issuance due to the change in AOCI in the quarter. | F9: {=_xldudf_BOARDFLARE_FMATCH(E9,'FS Consolidated Comments'!C$76:C$137,0.13)} -> #VALUE! | G9: {=_FV(F9,"Similarity")} -> 0 | H9: {=_FV(F9,"Match")}
A10: C:\Users\73335\OneDrive - Bain\Desktop\FS-ECR-repo\fs-earnings_call_reader\src\notebooks\submission_to_fs_6thAug\FS PDFs\American International Group Inc._Earnings Call_2023-05-05_English.pdf | B10: American International Group Inc. | C10: Macro factors | D10: Tag a commentary under the Macro Factors theme if it includes any reference—explicit or implicit—to the broader macroeconomic environment or external systemic influences affecting business performance. This includes mentions of economic slowdown, recession, uncertainty, market cycles, credit losses, or challenging operating conditions. Tag if the discussion involves monetary indicators such as inflation, interest rates (domestic or foreign), discount rates, investment yields, credit spreads, or currency and foreign exchange impacts. Also include insurance and financial-specific macro drivers such as mortality experience (including seasonal or pandemic-related surges), expected credit losses (ECL), movements in insurance liabilities, or gains/losses tied to market conditions. Furthermore, tag content that refers to external shocks like pandemics (e.g. COVID-19), natural disasters (e.g. hurricanes, floods), or geopolitical disruptions. Additionally, include discussions that indirectly reflect macro context—such as tough environments, changes in investor sentiment, demand volatility, or strategic repositioning in response to macro trends—even if specific macro terms are not used. | E10: 9. With respect to Corebridge, I took you through our current thinking on separation and timing of the secondary offerings. | F10: {=_xldudf_BOARDFLARE_FMATCH(E10,'FS Consolidated Comments'!C$76:C$137,0.13)} -> #VALUE! | G10: {=_FV(F10,"Similarity")} -> 0 | H10: {=_FV(F10,"Match")}
A11: C:\Users\73335\OneDrive - Bain\Desktop\FS-ECR-repo\fs-earnings_call_reader\src\notebooks\submission_to_fs_6thAug\FS PDFs\American International Group Inc._Earnings Call_2023-05-05_English.pdf | B11: American International Group Inc. | C11: Macro factors | D11: Tag a commentary under the Macro Factors theme if it includes any reference—explicit or implicit—to the broader macroeconomic environment or external systemic influences affecting business performance. This includes mentions of economic slowdown, recession, uncertainty, market cycles, credit losses, or challenging operating conditions. Tag if the discussion involves monetary indicators such as inflation, interest rates (domestic or foreign), discount rates, investment yields, credit spreads, or currency and foreign exchange impacts. Also include insurance and financial-specific macro drivers such as mortality experience (including seasonal or pandemic-related surges), expected credit losses (ECL), movements in insurance liabilities, or gains/losses tied to market conditions. Furthermore, tag content that refers to external shocks like pandemics (e.g. COVID-19), natural disasters (e.g. hurricanes, floods), or geopolitical disruptions. Additionally, include discussions that indirectly reflect macro context—such as tough environments, changes in investor sentiment, demand volatility, or strategic repositioning in response to macro trends—even if specific macro terms are not used. | E11: 10. We remain on track to reduce AIG common stock outstanding to be between 600 million and 650 million shares and achieve a debt-to-capital leverage at the lower end of our $20 \%$ to $25 \%$ range post deconsolidation of Corebridge. | F11: {=_xldudf_BOARDFLARE_FMATCH(E11,'FS Consolidated Comments'!C$76:C$137,0.13)} -> #VALUE! | G11: {=_FV(F11,"Similarity")} -> 0 | H11: {=_FV(F11,"Match")}
A12: C:\Users\73335\OneDrive - Bain\Desktop\FS-ECR-repo\fs-earnings_call_reader\src\notebooks\submission_to_fs_6thAug\FS PDFs\American International Group Inc._Earnings Call_2023-05-05_English.pdf | B12: American International Group Inc. | C12: Macro factors | D12: Tag a commentary under the Macro Factors theme if it includes any reference—explicit or implicit—to the broader macroeconomic environment or external systemic influences affecting business performance. This includes mentions of economic slowdown, recession, uncertainty, market cycles, credit losses, or challenging operating conditions. Tag if the discussion involves monetary indicators such as inflation, interest rates (domestic or foreign), discount rates, investment yields, credit spreads, or currency and foreign exchange impacts. Also include insurance and financial-specific macro drivers such as mortality experience (including seasonal or pandemic-related surges), expected credit losses (ECL), movements in insurance liabilities, or gains/losses tied to market conditions. Furthermore, tag content that refers to external shocks like pandemics (e.g. COVID-19), natural disasters (e.g. hurricanes, floods), or geopolitical disruptions. Additionally, include discussions that indirectly reflect macro context—such as tough environments, changes in investor sentiment, demand volatility, or strategic repositioning in response to macro trends—even if specific macro terms are not used. | E12: 11. We are confident that our continued progress on strategic initiatives and our capital management strategy will allow us to achieve our ROCE targets and deliver long-term profitable growth that benefits all of our stakeholders. | F12: {=_xldudf_BOARDFLARE_FMATCH(E12,'FS Consolidated Comments'!C$76:C$137,0.13)} -> #VALUE! | G12: {=_FV(F12,"Similarity")} -> 0 | H12: {=_FV(F12,"Match")}
A13: C:\Users\73335\OneDrive - Bain\Desktop\FS-ECR-repo\fs-earnings_call_reader\src\notebooks\submission_to_fs_6thAug\FS PDFs\American International Group Inc._Earnings Call_2023-05-05_English.pdf | B13: American International Group Inc. | C13: Macro factors | D13: Tag a commentary under the Macro Factors theme if it includes any reference—explicit or implicit—to the broader macroeconomic environment or external systemic influences affecting business performance. This includes mentions of economic slowdown, recession, uncertainty, market cycles, credit losses, or challenging operating conditions. Tag if the discussion involves monetary indicators such as inflation, interest rates (domestic or foreign), discount rates, investment yields, credit spreads, or currency and foreign exchange impacts. Also include insurance and financial-specific macro drivers such as mortality experience (including seasonal or pandemic-related surges), expected credit losses (ECL), movements in insurance liabilities, or gains/losses tied to market conditions. Furthermore, tag content that refers to external shocks like pandemics (e.g. COVID-19), natural disasters (e.g. hurricanes, floods), or geopolitical disruptions. Additionally, include discussions that indirectly reflect macro context—such as tough environments, changes in investor sentiment, demand volatility, or strategic repositioning in response to macro trends—even if specific macro terms are not used. | E13: 12. We sold and reinvested about $\$ 6$ billion in fixed maturities, resulting in a realized loss of $\$ 224$ million, but added 9 basis points of GI yield improvement for the quarter. | F13: {=_xldudf_BOARDFLARE_FMATCH(E13,'FS Consolidated Comments'!C$76:C$137,0.13)} -> #VALUE! | G13: {=_FV(F13,"Similarity")} -> 0 | H13: {=_FV(F13,"Match")}
... A81: C:\Users\73335\OneDrive - Bain\Desktop\FS-ECR-repo\fs-earnings_call_reader\src\notebooks\submission_to_fs_6thAug\FS PDFs\Manulife Financial Corporation_Earnings Call_2023-05-11_English.pdf | B81: Manulife Financial Corporation | C81: Macro factors | D81: Tag a commentary under the Macro Factors theme if it includes any reference—explicit or implicit—to the broader macroeconomic environment or external systemic influences affecting business performance. This includes mentions of economic slowdown, recession, uncertainty, market cycles, credit losses, or challenging operating conditions. Tag if the discussion involves monetary indicators such as inflation, interest rates (domestic or foreign), discount rates, investment yields, credit spreads, or currency and foreign exchange impacts. Also include insurance and financial-specific macro drivers such as mortality experience (including seasonal or pandemic-related surges), expected credit losses (ECL), movements in insurance liabilities, or gains/losses tied to market conditions. Furthermore, tag content that refers to external shocks like pandemics (e.g. COVID-19), natural disasters (e.g. hurricanes, floods), or geopolitical disruptions. Additionally, include discussions that indirectly reflect macro context—such as tough environments, changes in investor sentiment, demand volatility, or strategic repositioning in response to macro trends—even if specific macro terms are not used. | E81: 20. The market experienced losses in 2022 were primarily driven by lower-than-expected returns on public equity, net realized losses on fixed income investments and foreign exchange-related impacts, partially offset by net gains from hedge ineffectiveness and derivatives that were not in hedging relationships." | F81: {=_xldudf_BOARDFLARE_FMATCH(E81,'FS Consolidated Comments'!C$76:C$137,0.13)} -> #VALUE! | G81: {=_FV(F81,"Similarity")} -> 0 | H81: {=_FV(F81,"Match")}

Sheet FS Consolidated Comments
A1: Company | B1: Theme | C1: Commentary | D1: Page | E1: No-Match(0)/ | F1: Rationale for missing | G1: Conclusion
A2: Prudential | B2: Business/ top line growth | C2: Our Institutional Retirement Strategies business had strong first quarter sales, largely driven by our pension risk transfer business, which had its best first quarter ever with more than $2.8 billion in total new business transactions. | D2: 4 | E2: =COUNTIFS('[1]Consolidated Testing(7-10)'!$C:$C,B2,'[1]Consolidated Testing(7-10)'!$G:$G,C2,'[1]Consolidated Testing(7-10)'!$J:$J,1) -> 2 | F2: {=[2]Macro_Commentary_Classification!$C$2:$C$46} -> #VALUE!
A3: Prudential | B3: Business/ top line growth | C3: We also achieved new growth milestones in our international business, especially in Latin America, where Prudential of Brazil's sales reached double-digit year-over-year growth through our three distribution channels. | D3: 4 | E3: =COUNTIFS('[1]Consolidated Testing(7-10)'!$C:$C,B3,'[1]Consolidated Testing(7-10)'!$G:$G,C3,'[1]Consolidated Testing(7-10)'!$J:$J,1) -> 1 | F3: {=[2]Macro_Commentary_Classification!$C$2:$C$46} -> #VALUE!
A4: Prudential | B4: Business/ top line growth | C4: Our financial strength, including our AA rating is supported by $4.6 billion in highly liquid assets at the end of the first quarter as well as a high-quality, well-diversified investment portfolio and a disciplined approach to asset liability management. | D4: 5 | E4: =COUNTIFS('[1]Consolidated Testing(7-10)'!$C:$C,B4,'[1]Consolidated Testing(7-10)'!$G:$G,C4,'[1]Consolidated Testing(7-10)'!$J:$J,1) -> 0
A5: Prudential | B5: Business/ top line growth | C5: Our insurance and retirement businesses, in turn, provide a source of growth for PGIM through affiliated net flows, which totaled $2 billion in the first quarter of 2023 as well as unique access to insurance liabilities | D5: 6 | E5: =COUNTIFS('[1]Consolidated Testing(7-10)'!$C:$C,B5,'[1]Consolidated Testing(7-10)'!$G:$G,C5,'[1]Consolidated Testing(7-10)'!$J:$J,1) -> 0
A6: Prudential | B6: Macro factors | C6: These results reflect underlying business growth, including the benefits from a higher interest rate environment, offset by lower variable investment and fee income as well as elevated seasonal mortality experience | D6: 5 | E6: =COUNTIFS('[1]Consolidated Testing(7-10)'!$C:$C,B6,'[1]Consolidated Testing(7-10)'!$G:$G,C6,'[1]Consolidated Testing(7-10)'!$J:$J,1) -> 1 | F6: {=[2]Macro_Commentary_Classification!$C$2:$C$46} -> #VALUE!
A7: Prudential | B7: Business/ top line growth | C7: In Q1, we experienced third-party net outflows of $14 billion kind of driven both by Retail and Institutional. | D7: 9 | E7: =COUNTIFS('[1]Consolidated Testing(7-10)'!$C:$C,B7,'[1]Consolidated Testing(7-10)'!$G:$G,C7,'[1]Consolidated Testing(7-10)'!$J:$J,1) -> 1 | F7: {=[2]Macro_Commentary_Classification!$C$2:$C$46} -> #VALUE!
A8: Prudential | B8: Business/ top line growth | C8: And I'll just start with the institutional retirement business which ended the quarter with record account values of $253 billion. Our account values benefited from nearly $4 billion in sales, including the best first quarter ever in our pension risk transfer business | D8: 12 | E8: =COUNTIFS('[1]Consolidated Testing(7-10)'!$C:$C,B8,'[1]Consolidated Testing(7-10)'!$G:$G,C8,'[1]Consolidated Testing(7-10)'!$J:$J,1) -> 0
A9: Prudential | B9: Business/ top line growth | C9: In less than 3 years, we've delivered over $13 billion in total sales, clearly reinforcing our leadership position as a top 5 player in the indexed variable annuity space | D9: 12 | E9: =COUNTIFS('[1]Consolidated Testing(7-10)'!$C:$C,B9,'[1]Consolidated Testing(7-10)'!$G:$G,C9,'[1]Consolidated Testing(7-10)'!$J:$J,1) -> 0
A10: Prudential | B10: Business/ top line growth | C10: So let me just start by taking a step back and pointing out that at core focus, our group business is to remain price disciplined and profit focused. And that just really means pursuing smart growth. We saw a 2% growth from the year ago quarter and earned premiums and fees, and that was primarily driven by growth in disability and supplemental health. | D10: 13 | E10: =COUNTIFS('[1]Consolidated Testing(7-10)'!$C:$C,B10,'[1]Consolidated Testing(7-10)'!$G:$G,C10,'[1]Consolidated Testing(7-10)'!$J:$J,1) -> 0
A11: Prudential | B11: M&A | C11: We did programmatic M&A with the Deerpath Capital, we returned capital to shareholders, both in the form of dividends and share repurchases and we made an announcement to repay hybrid, which lowers our -- the hybrid, which lowers our leverage. | D11: 11 | E11: =COUNTIFS('[1]Consolidated Testing(7-10)'!$C:$C,B11,'[1]Consolidated Testing(7-10)'!$G:$G,C11,'[1]Consolidated Testing(7-10)'!$J:$J,1) -> 2 | F11: {=[2]Macro_Commentary_Classification!$C$2:$C$46} -> #VALUE!
A12: Manulife | B12: Business/ top line growth | C12: "Our North American insurance businesses generated strong core earnings growth compared with the prior year quarter, and we're encouraged by the momentum building in Asia." | D12: 8 | E12: =COUNTIFS('[1]Consolidated Testing(7-10)'!$C:$C,B12,'[1]Consolidated Testing(7-10)'!$G:$G,C12,'[1]Consolidated Testing(7-10)'!$J:$J,1) -> 0
A13: Manulife | B13: Business/ top line growth | C13: "Of note, Hong Kong APE sales increased 26% from the prior year quarter, reflecting a return of demand from Mainland Chinese visitors, or MCV, following the border reopening between Hong Kong and Mainland China during the quarter. And our domestic Hong Kong business remained strong with a 21% increase in sales quarter-over-quarter." | D13: 8 | E13: =COUNTIFS('[1]Consolidated Testing(7-10)'!$C:$C,B13,'[1]Consolidated Testing(7-10)'!$G:$G,C13,'[1]Consolidated Testing(7-10)'!$J:$J,1) -> 0
A14: Manulife | B14: Business/ top line growth | C14: "Core earnings in Canada increased by 6%, reflecting improved insurance experience, higher expected investment spreads and higher Manulife Bank earnings, partially offset by slower amortization of CSM." | D14: 10 | E14: =COUNTIFS('[1]Consolidated Testing(7-10)'!$C:$C,B14,'[1]Consolidated Testing(7-10)'!$G:$G,C14,'[1]Consolidated Testing(7-10)'!$J:$J,1) -> 0
A15: Manulife | B15: Business/ top line growth | C15: "In fact, our APE sales quarter-on-quarter grew 22% in Q1 versus Q4 and Asia grew 28% quarter-on-quarter. And throughout the first quarter, we saw consistent and stable increase in sales momentum, which came off the back of the restrictions being lifted." | D15: 13 | E15: =COUNTIFS('[1]Consolidated Testing(7-10)'!$C:$C,B15,'[1]Consolidated Testing(7-10)'!$G:$G,C15,'[1]Consolidated Testing(7-10)'!$J:$J,1) -> 0
A16: Manulife | B16: Business/ top line growth | C16: "And as we see that sales momentum pick up, not just in Asia but across all of our franchise, getting back to new business CSM growth at 15% and then total CSM balance growth of 8% to 10% is definitely still something we feel very confident about and certainly through our medium-term focus and targets, that's where we'd like to be, and we see ourselves." | D16: 18 | E16: =COUNTIFS('[1]Consolidated Testing(7-10)'!$C:$C,B16,'[1]Consolidated Testing(7-10)'!$G:$G,C16,'[1]Consolidated Testing(7-10)'!$J:$J,1) -> 0
A17: Manulife | B17: Business/ top line growth | C17: "The core net investment result increased 14% from the prior year quarter, driven by higher expected investment earnings, which reflects both portfolio growth and higher reinvestment yields. In addition, higher interest rates contributed to higher earnings on surplus assets." | D17: 9 | E17: =COUNTIFS('[1]Consolidated Testing(7-10)'!$C:$C,B17,'[1]Consolidated Testing(7-10)'!$G:$G,C17,'[1]Consolidated Testing(7-10)'!$J:$J,1) -> 0
A18: Manulife | B18: Business/ top line growth | C18: "Our embedded value of $63.9 billion or $34.29 per common share grew $0.94 per share in 2022, supported by robust organic growth of 11.7%." | D18: 9 | E18: =COUNTIFS('[1]Consolidated Testing(7-10)'!$C:$C,B18,'[1]Consolidated Testing(7-10)'!$G:$G,C18,'[1]Consolidated Testing(7-10)'!$J:$J,1) -> 0
A19: AIG | B19: Business/ top line growth | C19: Gross premiums written were $12 billion, an increase of 9%, with Global Commercial growing 13% and Global Personal decreasing 4%. Net premiums written were $7 billion, an increase of 10%. This growth was primarily driven by Global Commercial, which grew 11%, while Global Personal grew 6%. | D19: 5 | E19: =COUNTIFS('[1]Consolidated Testing(7-10)'!$C:$C,B19,'[1]Consolidated Testing(7-10)'!$G:$G,C19,'[1]Consolidated Testing(7-10)'!$J:$J,1) -> 0
A20: Prudential | B20: M&A | C20: Yesterday, we announced that Prudential is acquiring a majority stake in Deerpath Capital Management, a leading U.S. private credit and direct lending manager with more than $5 billion in assets under management. | D20: 4 | E20: =COUNTIFS('[1]Consolidated Testing(7-10)'!$C:$C,B20,'[1]Consolidated Testing(7-10)'!$G:$G,C20,'[1]Consolidated Testing(7-10)'!$J:$J,1) -> 2 | F20: {=[2]Macro_Commentary_Classification!$C$2:$C$46} -> #VALUE!
A21: Prudential | B21: Tech transformation | C21: First, an industry survey ranked Prudential as a top 3 carrier in e-signature adoption. A majority of annuities applications are now submitted with e-signature, which has reduced processing time by several days and improved our environmental impact. | D21: 5 | E21: =COUNTIFS('[1]Consolidated Testing(7-10)'!$C:$C,B21,'[1]Consolidated Testing(7-10)'!$G:$G,C21,'[1]Consolidated Testing(7-10)'!$J:$J,1) -> 1 | F21: {=[2]Macro_Commentary_Classification!$C$2:$C$46} -> #VALUE!
A22: AIG | B22: Business/ top line growth | C22: In North America Commercial, we saw a very strong growth of 15% in net premiums written due to Validus Re, which had over 40% growth year-over-year due to the exceptional results we achieved with our January 1 treaty placements, which I discussed in detail on our last call | D22: 5 | E22: =COUNTIFS('[1]Consolidated Testing(7-10)'!$C:$C,B22,'[1]Consolidated Testing(7-10)'!$G:$G,C22,'[1]Consolidated Testing(7-10)'!$J:$J,1) -> 0
A23: AIG | B23: Business/ top line growth | C23: Strong retention, new business and rate have been the key drivers of Lexington's financial performance. Lexington has now seen double-digit rate increases for 16 consecutive quarters, and cumulative compounded rate increases totaled over 100% since the first quarter of 2018. | D23: 5 | E23: =COUNTIFS('[1]Consolidated Testing(7-10)'!$C:$C,B23,'[1]Consolidated Testing(7-10)'!$G:$G,C23,'[1]Consolidated Testing(7-10)'!$J:$J,1) -> 0
A24: Prudential | B24: Operational/ cost efficiency | C24: And then finally, we remain focused on expense discipline. and continuous improvement in operating efficiency with an eye towards protecting the bottom line. | D24: 12 | E24: =COUNTIFS('[1]Consolidated Testing(7-10)'!$C:$C,B24,'[1]Consolidated Testing(7-10)'!$G:$G,C24,'[1]Consolidated Testing(7-10)'!$J:$J,1) -> 1 | F24: {=[2]Macro_Commentary_Classification!$C$2:$C$46} -> #VALUE!
A25: Prudential | B25: Product Expansion | C25: . In the U.S., our individual retirement strategies business continued to expand its suite of next-generation protection solutions. We expanded our FlexGuard distribution and introduced new product enhancements to meet the evolving needs of our customers | D25: 4 | E25: =COUNTIFS('[1]Consolidated Testing(7-10)'!$C:$C,B25,'[1]Consolidated Testing(7-10)'!$G:$G,C25,'[1]Consolidated Testing(7-10)'!$J:$J,1) -> 2 | F25: {=[2]Macro_Commentary_Classification!$C$2:$C$46} -> #VALUE!
A26: AIG | B26: Business/ top line growth | C26: Additionally, over the last few years, the average size of a Lexington Property primary policy went from $100 million in limits deployed to $5 million. | D26: 5 | E26: =COUNTIFS('[1]Consolidated Testing(7-10)'!$C:$C,B26,'[1]Consolidated Testing(7-10)'!$G:$G,C26,'[1]Consolidated Testing(7-10)'!$J:$J,1) -> 0
A27: AIG | B27: Business/ top line growth | C27: Net premiums written were very strong and balanced in Validus Re, and we continue to meaningfully improve the quality of the portfolio. Rate improvements were particularly strong in U.S. Property, International Property, Marine and Energy, Casualty and Specialty Lines. | D27: 5 | E27: =COUNTIFS('[1]Consolidated Testing(7-10)'!$C:$C,B27,'[1]Consolidated Testing(7-10)'!$G:$G,C27,'[1]Consolidated Testing(7-10)'!$J:$J,1) -> 0
A28: Prudential | B28: Product Expansion | C28: We do continue to believe that this business is core to Prudential's purpose and we like the growth potential with our overall brand as well as our product breadth and certainly our distribution strength. | D28: 10 | E28: =COUNTIFS('[1]Consolidated Testing(7-10)'!$C:$C,B28,'[1]Consolidated Testing(7-10)'!$G:$G,C28,'[1]Consolidated Testing(7-10)'!$J:$J,1) -> 1 | F28: {=[2]Macro_Commentary_Classification!$C$2:$C$46} -> #VALUE!
A29: Prudential | B29: Product Expansion | C29: our work on innovating our product designs continues as we drive to ensure that we meet the needs for retirement, wealth transfer and unmet health and care needs. | D29: 14 | E29: =COUNTIFS('[1]Consolidated Testing(7-10)'!$C:$C,B29,'[1]Consolidated Testing(7-10)'!$G:$G,C29,'[1]Consolidated Testing(7-10)'!$J:$J,1) -> 1 | F29: {=[2]Macro_Commentary_Classification!$C$2:$C$46} -> #VALUE!
A30: Prudential | B30: Regulatory or accounting update | C30: Yes, the NAIC is in the process of addressing what is uneconomic issues with the IMR. They -- as you mentioned, they've released a proposal, and that's out for comment until June 9. | D30: 8 | E30: =COUNTIFS('[1]Consolidated Testing(7-10)'!$C:$C,B30,'[1]Consolidated Testing(7-10)'!$G:$G,C30,'[1]Consolidated Testing(7-10)'!$J:$J,1) -> 1 | F30: {=[2]Macro_Commentary_Classification!$C$2:$C$46} -> #VALUE!
A31: Prudential | B31: Regulatory or accounting update | C31: So obviously, as you state, LDTI is expected to result in a meaningful decline in earnings this year for the Life business as AOI recognition will be deferred | D31: 10 | E31: =COUNTIFS('[1]Consolidated Testing(7-10)'!$C:$C,B31,'[1]Consolidated Testing(7-10)'!$G:$G,C31,'[1]Consolidated Testing(7-10)'!$J:$J,1) -> 1 | F31: {=[2]Macro_Commentary_Classification!$C$2:$C$46} -> #VALUE!
A32: AIG | B32: Business/ top line growth | C32: Turning to International Commercial. Net premiums written grew 6%, primarily due to Property, which was up over 40%; Global Specialty, which was up over 15%; and Casualty, which was up over 15%. Global Commercial had very strong renewal retention of 88% in its in-force portfolio, International was up 200 basis points to 88%, and North America was up 100 basis points to 87% | D32: 6 | E32: =COUNTIFS('[1]Consolidated Testing(7-10)'!$C:$C,B32,'[1]Consolidated Testing(7-10)'!$G:$G,C32,'[1]Consolidated Testing(7-10)'!$J:$J,1) -> 0
A33: Manulife | B33: Macro factors | C33: "Our result reflects the quality of our fixed income portfolio amid a challenging global macroeconomic environment in 2022." | D33: 6 | E33: =COUNTIFS('[1]Consolidated Testing(7-10)'!$C:$C,B33,'[1]Consolidated Testing(7-10)'!$G:$G,C33,'[1]Consolidated Testing(7-10)'!$J:$J,1) -> 1 | F33: {=[2]Macro_Commentary_Classification!$C$2:$C$46} -> #VALUE! | H33: =[2]Macro_Commentary_Classification!$C10 -> Not Relevant
A34: AIG | B34: Business/ top line growth | C34: International Commercial new business was over $590 million, led by Specialty, which increased its new business by over 50%, driven by Energy and Marine. North America Commercial, excluding Validus Re, achieved new business of over $480 million, driven by Lexington, which saw excellent new business growth of over 50%. | D34: 6 | E34: =COUNTIFS('[1]Consolidated Testing(7-10)'!$C:$C,B34,'[1]Consolidated Testing(7-10)'!$G:$G,C34,'[1]Consolidated Testing(7-10)'!$J:$J,1) -> 0 | H34: =[2]Macro_Commentary_Classification!$C11 -> Relevant
A35: AIG | B35: Business/ top line growth | C35: The combination of improved pricing in our admitted business and more business migrating to the non-admitting market has a very positive impact on PCG's accident and policy or loss ratios. | D35: 6 | E35: =COUNTIFS('[1]Consolidated Testing(7-10)'!$C:$C,B35,'[1]Consolidated Testing(7-10)'!$G:$G,C35,'[1]Consolidated Testing(7-10)'!$J:$J,1) -> 0
A36: Prudential | B36: Tech transformation | C36: We continue to enhance the ways in which customers engage with our products and solutions to drive more digital experiences and better customer outcomes. | D36: 5 | E36: =COUNTIFS('[1]Consolidated Testing(7-10)'!$C:$C,B36,'[1]Consolidated Testing(7-10)'!$G:$G,C36,'[1]Consolidated Testing(7-10)'!$J:$J,1) -> 2 | F36: {=[2]Macro_Commentary_Classification!$C$2:$C$46} -> #VALUE!
A37: Manulife | B37: Macro factors | C37: "We expect the magnitude of market experience impact to reduce going forward." | D37: 6 | E37: =COUNTIFS('[1]Consolidated Testing(7-10)'!$C:$C,B37,'[1]Consolidated Testing(7-10)'!$G:$G,C37,'[1]Consolidated Testing(7-10)'!$J:$J,1) -> 2 | F37: {=[2]Macro_Commentary_Classification!$C$2:$C$46} -> #VALUE!
A38: AIG | B38: Business/ top line growth | C38: Turning to International Personal. Net premiums written were largely flat in the first quarter, Travel and Warranty grew while Personal Property declined, all driven by a further refinement of our cat reinsurance cost allocation methodology, making year-overyear comparisons difficult | D38: 7 | E38: =COUNTIFS('[1]Consolidated Testing(7-10)'!$C:$C,B38,'[1]Consolidated Testing(7-10)'!$G:$G,C38,'[1]Consolidated Testing(7-10)'!$J:$J,1) -> 0
A39: AIG | B39: Business/ top line growth | C39: As I mentioned earlier, premiums and deposits grew significantly in the first quarter, driven by strong new individual retirement business, which, despite increasing surrenders related to interest rates, contributed to growth in the General Account. | D39: 7 | E39: =COUNTIFS('[1]Consolidated Testing(7-10)'!$C:$C,B39,'[1]Consolidated Testing(7-10)'!$G:$G,C39,'[1]Consolidated Testing(7-10)'!$J:$J,1) -> 0
A40: Manulife | B40: Macro factors | C40: "We reported strong operating results against the challenging backdrop of market volatility, persistent inflation, continued recession concerns and stress in the banking sector." | D40: 8 | E40: =COUNTIFS('[1]Consolidated Testing(7-10)'!$C:$C,B40,'[1]Consolidated Testing(7-10)'!$G:$G,C40,'[1]Consolidated Testing(7-10)'!$J:$J,1) -> 1 | F40: {=[2]Macro_Commentary_Classification!$C$2:$C$46} -> #VALUE!
A41: AIG | B41: Business/ top line growth | C41: As I discussed earlier, our first quarter financial results were excellent, with continued top line growth and improvement in underwriting profitability in General Insurance. Over the last few months, we accelerated our work to establish AIG's future state business model. | D41: 8 | E41: =COUNTIFS('[1]Consolidated Testing(7-10)'!$C:$C,B41,'[1]Consolidated Testing(7-10)'!$G:$G,C41,'[1]Consolidated Testing(7-10)'!$J:$J,1) -> 0
A42: AIG | B42: Business/ top line growth | C42: Turning to the segments. GI adjusted pretax income, or APTI, was $1.2 billion, $37 million higher than 1Q '22, principally due to a $56 million increase in underwriting income from both higher-earned premiums and a 1 point improvement in the calendar year combined ratio, which was 91.9%. | D42: 9 | E42: =COUNTIFS('[1]Consolidated Testing(7-10)'!$C:$C,B42,'[1]Consolidated Testing(7-10)'!$G:$G,C42,'[1]Consolidated Testing(7-10)'!$J:$J,1) -> 0
A43: Manulife | B43: Macro factors | C43: "With office real estate under some cyclical and secular pressures, there could be further declines in this asset class if conditions in the macro environments deteriorate further." | D43: 10 | E43: =COUNTIFS('[1]Consolidated Testing(7-10)'!$C:$C,B43,'[1]Consolidated Testing(7-10)'!$G:$G,C43,'[1]Consolidated Testing(7-10)'!$J:$J,1) -> 1 | F43: {=[2]Macro_Commentary_Classification!$C$2:$C$46} -> #VALUE!
A44: AIG | B44: Business/ top line growth | C44: Turning to L&R results for the first quarter. APTI was $886 million, down $48 million compared to $934 million in 1Q '22 as restated | D44: 9 | E44: =COUNTIFS('[1]Consolidated Testing(7-10)'!$C:$C,B44,'[1]Consolidated Testing(7-10)'!$G:$G,C44,'[1]Consolidated Testing(7-10)'!$J:$J,1) -> 0
A45: AIG | B45: Business/ top line growth | C45: As Peter noted, L&R premiums and deposits were very strong at $10.4 billion. Notably, Individual Retirement sales were $4.9 billion, a 26% increase over the prior year quarter with record levels of fixed and fixed index annuity sales because of higher crediting rates. | D45: 9 | E45: =COUNTIFS('[1]Consolidated Testing(7-10)'!$C:$C,B45,'[1]Consolidated Testing(7-10)'!$G:$G,C45,'[1]Consolidated Testing(7-10)'!$J:$J,1) -> 0
A46: AIG | B46: Business/ top line growth | C46: Group Retirement deposits grew 19%, with higher out-of-plan fixed annuity sales and new plan acquisitions. | D46: 9 | E46: =COUNTIFS('[1]Consolidated Testing(7-10)'!$C:$C,B46,'[1]Consolidated Testing(7-10)'!$G:$G,C46,'[1]Consolidated Testing(7-10)'!$J:$J,1) -> 0
A47: AIG | B47: Business/ top line growth | C47: To conclude on earnings for the quarter, other operations adjusted pretax loss, or APTL, was $491 million, a $70 million increase due to lower APTI from consolidated investment entities in Asset Management, which had strong private equity results in 1Q '22. | D47: 9 | E47: =COUNTIFS('[1]Consolidated Testing(7-10)'!$C:$C,B47,'[1]Consolidated Testing(7-10)'!$G:$G,C47,'[1]Consolidated Testing(7-10)'!$J:$J,1) -> 0
A48: AIG | B48: Business/ top line growth | C48: While the top line that we publish on a gross and net basis is significant, that's gone up 40%, 50%, if not more, over the past several years based on those components. | D48: 14 | E48: =COUNTIFS('[1]Consolidated Testing(7-10)'!$C:$C,B48,'[1]Consolidated Testing(7-10)'!$G:$G,C48,'[1]Consolidated Testing(7-10)'!$J:$J,1) -> 0
A49: AIG | B49: Business/ top line growth | C49: Turning to Life and Retirement. The business delivered strong performance in the first quarter. Adjusted pretax income was $886 million for the first quarter, and adjusted return on segment equity was 10.7%. | D49: 7 | E49: =COUNTIFS('[1]Consolidated Testing(7-10)'!$C:$C,B49,'[1]Consolidated Testing(7-10)'!$G:$G,C49,'[1]Consolidated Testing(7-10)'!$J:$J,1) -> 0
A50: Manulife | B50: Regulatory or accounting update | C50: "While IFRS 17 does not impact the fundamental economics of our business or financial strength, the new accounting standards are expected to improve the stability of our financial metrics." | D50: 4 | E50: =COUNTIFS('[1]Consolidated Testing(7-10)'!$C:$C,B50,'[1]Consolidated Testing(7-10)'!$G:$G,C50,'[1]Consolidated Testing(7-10)'!$J:$J,1) -> 2 | F50: {=[2]Macro_Commentary_Classification!$C$2:$C$46} -> #VALUE!
A51: Manulife | B51: Business/ top line growth | C51: "We delivered solid core earnings of $5.8 billion despite the claims experienced losses in our U.S. Life business due to COVID-19 and charges in our property and casualty reinsurance business due to Hurricane Ian." | D51: 4 | E51: =COUNTIFS('[1]Consolidated Testing(7-10)'!$C:$C,B51,'[1]Consolidated Testing(7-10)'!$G:$G,C51,'[1]Consolidated Testing(7-10)'!$J:$J,1) -> 1 | F51: {=[2]Macro_Commentary_Classification!$C$2:$C$46} -> #VALUE!
A52: AIG | B52: Business/ top line growth | C52: In terms of expectations for PCG for the full year, we expect net premiums written growth to be at or higher than we saw in the first quarter, the loss ratio to meaningfully improve and the acquisition ratio and general operating expense to also improve. | D52: 6 | E52: =COUNTIFS('[1]Consolidated Testing(7-10)'!$C:$C,B52,'[1]Consolidated Testing(7-10)'!$G:$G,C52,'[1]Consolidated Testing(7-10)'!$J:$J,1) -> 0
A53: Manulife | B53: Business/ top line growth | C53: "We delivered new business CSM of $1.9 billion in 2022, reflecting the profitable growth of our insurance businesses globally." | D53: 4 | E53: =COUNTIFS('[1]Consolidated Testing(7-10)'!$C:$C,B53,'[1]Consolidated Testing(7-10)'!$G:$G,C53,'[1]Consolidated Testing(7-10)'!$J:$J,1) -> 2 | F53: {=[2]Macro_Commentary_Classification!$C$2:$C$46} -> #VALUE!
A54: Manulife | B54: Regulatory or accounting update | C54: "And our capital remains strong with a LICAT ratio of 136% under IFRS 17, an increase of 5 percentage points relative to IFRS 4, reflecting a more stable capital ratio relative to interest rate movements under the new accounting regime." | D54: 4 | E54: =COUNTIFS('[1]Consolidated Testing(7-10)'!$C:$C,B54,'[1]Consolidated Testing(7-10)'!$G:$G,C54,'[1]Consolidated Testing(7-10)'!$J:$J,1) -> 1 | F54: {=[2]Macro_Commentary_Classification!$C$2:$C$46} -> #VALUE!
A55: Metlife | B55: Business/ top line growth | C55: "Sales on a constant currency basis were up across the board in the region. Japan saw sales rise 17% on the strength of FX annuities, while India led the sales gains in other Asia, up 45%, followed by Korea, up 21%." | D55: 4 | E55: =COUNTIFS('[1]Consolidated Testing(7-10)'!$C:$C,B55,'[1]Consolidated Testing(7-10)'!$G:$G,C55,'[1]Consolidated Testing(7-10)'!$J:$J,1) -> 0
A56: Metlife | B56: Business/ top line growth | C56: "And our business continues to put up impressive growth numbers in our major markets with sales jumping 36% and adjusted PFOs rising 26%, both on a constant currency basis" | D56: 5 | E56: =COUNTIFS('[1]Consolidated Testing(7-10)'!$C:$C,B56,'[1]Consolidated Testing(7-10)'!$G:$G,C56,'[1]Consolidated Testing(7-10)'!$J:$J,1) -> 0
A57: Metlife | B57: Business/ top line growth | C57: "Turning to the top line. Group Benefits adjusted PFOs were up 1% year-over-year." | D57: 6 | E57: =COUNTIFS('[1]Consolidated Testing(7-10)'!$C:$C,B57,'[1]Consolidated Testing(7-10)'!$G:$G,C57,'[1]Consolidated Testing(7-10)'!$J:$J,1) -> 0
A58: Metlife | B58: Business/ top line growth | C58: "In addition, Group Benefits sales were up 15%, driven by strong growth across all markets." | D58: 6 | E58: =COUNTIFS('[1]Consolidated Testing(7-10)'!$C:$C,B58,'[1]Consolidated Testing(7-10)'!$G:$G,C58,'[1]Consolidated Testing(7-10)'!$J:$J,1) -> 0
A59: Metlife | B59: Business/ top line growth | C59: "Let me conclude by saying that MetLife's results reflect the strength of our business fundamentals: solid top line growth, favorable underwriting and ongoing expense discipline" | D59: 8 | E59: =COUNTIFS('[1]Consolidated Testing(7-10)'!$C:$C,B59,'[1]Consolidated Testing(7-10)'!$G:$G,C59,'[1]Consolidated Testing(7-10)'!$J:$J,1) -> 0
A60: Metlife | B60: Business/ top line growth | C60: "In addition, results in our market-leading franchises, Group Benefits and Latin America, continued their strong top and bottom line growth." | D60: 8 | E60: =COUNTIFS('[1]Consolidated Testing(7-10)'!$C:$C,B60,'[1]Consolidated Testing(7-10)'!$G:$G,C60,'[1]Consolidated Testing(7-10)'!$J:$J,1) -> 0
A61: Metlife | B61: Business/ top line growth | C61: "We are market leaders with a very strong brand in Mexico and Chile and a very fast-growing presence in Brazil." | D61: 10 | E61: =COUNTIFS('[1]Consolidated Testing(7-10)'!$C:$C,B61,'[1]Consolidated Testing(7-10)'!$G:$G,C61,'[1]Consolidated Testing(7-10)'!$J:$J,1) -> 0
A62: Metlife | B62: Business/ top line growth | C62: "And then in Brazil, which now represents roughly 20% of the region's sales, we're also growing very, very fast with 60% year-over-year this quarter alone" | D62: 10 | E62: =COUNTIFS('[1]Consolidated Testing(7-10)'!$C:$C,B62,'[1]Consolidated Testing(7-10)'!$G:$G,C62,'[1]Consolidated Testing(7-10)'!$J:$J,1) -> 0
A63: Metlife | B63: Business/ top line growth | C63: "EMEA adjusted PFOs were up 5% on a constant currency basis and sales were up 27% on a constant currency basis, reflecting strong growth across the region." | D63: 6 | E63: =COUNTIFS('[1]Consolidated Testing(7-10)'!$C:$C,B63,'[1]Consolidated Testing(7-10)'!$G:$G,C63,'[1]Consolidated Testing(7-10)'!$J:$J,1) -> 0
A64: Metlife | B64: Business/ top line growth | C64: "Our persistency in terms of the Q1 renewals was extremely strong, and it was higher than prior year across all of our major markets." | D64: 12 | E64: =COUNTIFS('[1]Consolidated Testing(7-10)'!$C:$C,B64,'[1]Consolidated Testing(7-10)'!$G:$G,C64,'[1]Consolidated Testing(7-10)'!$J:$J,1) -> 0
A65: Manulife | B65: M&A | C65: "Our core EBITDA margin decreased to 22.4% in the quarter, reflecting the factors I noted earlier on core earnings as well as the modest impact from the acquisition of full ownership in Manulife Fund Management in Mainland China as its general expenses are now consolidated." | D65: 11 | E65: =COUNTIFS('[1]Consolidated Testing(7-10)'!$C:$C,B65,'[1]Consolidated Testing(7-10)'!$G:$G,C65,'[1]Consolidated Testing(7-10)'!$J:$J,1) -> 0
A66: Manulife | B66: M&A | C66: "The other thing I would call out is that there's also an impact this quarter from the consolidation that Phil talked about as it relates to our China acquisition, now called Manulife Fund Management." | D66: 22 | E66: =COUNTIFS('[1]Consolidated Testing(7-10)'!$C:$C,B66,'[1]Consolidated Testing(7-10)'!$G:$G,C66,'[1]Consolidated Testing(7-10)'!$J:$J,1) -> 0
A67: Manulife | B67: Macro factors | C67: "Our financial strength and stability are as important as ever as the macro backdrop remains uncertain." | D67: 9 | E67: =COUNTIFS('[1]Consolidated Testing(7-10)'!$C:$C,B67,'[1]Consolidated Testing(7-10)'!$G:$G,C67,'[1]Consolidated Testing(7-10)'!$J:$J,1) -> 1 | F67: {=[2]Macro_Commentary_Classification!$C$2:$C$46} -> #VALUE!
A68: AIG | B68: Macro factors | C68: We continue to make meaningful progress across AIG and achieve important milestones, even in the face of ongoing complexity in the insurance industry, volatile market conditions and general economic uncertainty | D68: 4 | E68: =COUNTIFS('[1]Consolidated Testing(7-10)'!$C:$C,B68,'[1]Consolidated Testing(7-10)'!$G:$G,C68,'[1]Consolidated Testing(7-10)'!$J:$J,1) -> 1 | F68: {=[2]Macro_Commentary_Classification!$C$2:$C$46} -> #VALUE!
A69: Manulife | B69: M&A | C69: "The first is we're already starting to see some positive momentum of the acquisition and the new leadership team we put in place of the positive flows in the quarter, $1.8 billion came from China in Q1, and a lot of that was driven by a very large fundraise they were able to complete." | D69: 22 | E69: =COUNTIFS('[1]Consolidated Testing(7-10)'!$C:$C,B69,'[1]Consolidated Testing(7-10)'!$G:$G,C69,'[1]Consolidated Testing(7-10)'!$J:$J,1) -> 0
A70: AIG | B70: M&A | C70: Corebridge and Blackstone have made substantial progress advancing their strategic partnership, which began in late 2021. Since that time, Blackstone has invested approximately $11 billion on behalf of Corebridge, with an average gross yield of 6.5% and an average credit rating of A | D70: 4 | E70: =COUNTIFS('[1]Consolidated Testing(7-10)'!$C:$C,B70,'[1]Consolidated Testing(7-10)'!$G:$G,C70,'[1]Consolidated Testing(7-10)'!$J:$J,1) -> 0
A71: AIG | B71: M&A | C71: We continue to be prepared and disciplined in terms of executing a secondary offering, which remains our base case for selling down our ownership in Corebridge, subject to market conditions and regulatory approvals. We remain committed to reducing our ownership interest in Corebridge and will explore other options that are aligned with the best interest of shareholders. | D71: 5 | E71: =COUNTIFS('[1]Consolidated Testing(7-10)'!$C:$C,B71,'[1]Consolidated Testing(7-10)'!$G:$G,C71,'[1]Consolidated Testing(7-10)'!$J:$J,1) -> 0
A72: AIG | B72: M&A | C72: First quarter results reflect our continued repositioning of this business, especially PCG, given our announcement of the creation of a managing general agency in partnership with Stone Point Capital. | D72: 6 | E72: =COUNTIFS('[1]Consolidated Testing(7-10)'!$C:$C,B72,'[1]Consolidated Testing(7-10)'!$G:$G,C72,'[1]Consolidated Testing(7-10)'!$J:$J,1) -> 0
A73: AIG | B73: M&A | C73: We acquired CRS as part of our broader acquisition of Validus Holdings in 2018. AIG will continue to write business for the 2023 spring crop season, which ends June 30 | D73: 7 | E73: =COUNTIFS('[1]Consolidated Testing(7-10)'!$C:$C,B73,'[1]Consolidated Testing(7-10)'!$G:$G,C73,'[1]Consolidated Testing(7-10)'!$J:$J,1) -> 0
A74: Manulife | B74: Business/ top line growth | C74: "Our APE sales were $1.6 billion, supported by sales growth in Asia, which increased 5% from the prior year quarter, and we saw sales momentum building throughout the first quarter." | D74: 8 | E74: =COUNTIFS('[1]Consolidated Testing(7-10)'!$C:$C,B74,'[1]Consolidated Testing(7-10)'!$G:$G,C74,'[1]Consolidated Testing(7-10)'!$J:$J,1) -> 2 | F74: {=[2]Macro_Commentary_Classification!$C$2:$C$46} -> #VALUE!
A75: AIG | B75: M&A | C75: In American Financial Group, we have found a high-quality partner for CRS and its employees and believe the business will benefit from being part of a larger combined platform. | D75: 7 | E75: =COUNTIFS('[1]Consolidated Testing(7-10)'!$C:$C,B75,'[1]Consolidated Testing(7-10)'!$G:$G,C75,'[1]Consolidated Testing(7-10)'!$J:$J,1) -> 0
A76: Prudential | B76: Macro factors | C76: As you know, last quarter, we lowered our run rate expectations for ORR, specifically due to as you're speaking to the expected slowdown in real estate-related revenues. | D76: 9 | E76: =COUNTIFS('[1]Consolidated Testing(7-10)'!$C:$C,B76,'[1]Consolidated Testing(7-10)'!$G:$G,C76,'[1]Consolidated Testing(7-10)'!$J:$J,1) -> 0
A77: Prudential | B77: Macro factors | C77: So in the quarter, we came in lower than our expected average because we saw that real estate slowdown as we expect it. And I guess the only other thing I would mention is, just a reminder that incentive fees tend to be seasonally low in Q1. | D77: 9 | E77: =COUNTIFS('[1]Consolidated Testing(7-10)'!$C:$C,B77,'[1]Consolidated Testing(7-10)'!$G:$G,C77,'[1]Consolidated Testing(7-10)'!$J:$J,1) -> 0
A78: Prudential | B78: Macro factors | C78: what is underpinning our plans is sort of the expectation of a slowing economy and the early stages of a mild recession, which would include an elevated level of credit losses and in-rating migration. | D78: 10 | E78: =COUNTIFS('[1]Consolidated Testing(7-10)'!$C:$C,B78,'[1]Consolidated Testing(7-10)'!$G:$G,C78,'[1]Consolidated Testing(7-10)'!$J:$J,1) -> 0
A79: Prudential | B79: Macro factors | C79: We're seeing tight labor markets with low current unemployment and a large number of job openings. | D79: 13 | E79: =COUNTIFS('[1]Consolidated Testing(7-10)'!$C:$C,B79,'[1]Consolidated Testing(7-10)'!$G:$G,C79,'[1]Consolidated Testing(7-10)'!$J:$J,1) -> 0
A80: Prudential | B80: Macro factors | C80: And another question around Japan. I believe they're lifting pandemic-related restrictions, categorizing COVID like infectious disease or like the influenza. | D80: 13 | E80: =COUNTIFS('[1]Consolidated Testing(7-10)'!$C:$C,B80,'[1]Consolidated Testing(7-10)'!$G:$G,C80,'[1]Consolidated Testing(7-10)'!$J:$J,1) -> 0
A81: Prudential | B81: Macro factors | C81: As far as the higher rates, and obviously, when we say that, higher Yen rates, higher U.S. interest rates, I would -- as I would always say, higher interest rates are good for Prudential, are good for our businesses, and they're good for our Japanese business. | D81: 15 | E81: =COUNTIFS('[1]Consolidated Testing(7-10)'!$C:$C,B81,'[1]Consolidated Testing(7-10)'!$G:$G,C81,'[1]Consolidated Testing(7-10)'!$J:$J,1) -> 0
A82: Manulife | B82: Business/ top line growth | C82: "Core earnings in the U.S. increased by 23%, reflecting improved insurance experience, increased expected investment earnings and lower onerous losses on new insurance business." | D82: 10 | E82: =COUNTIFS('[1]Consolidated Testing(7-10)'!$C:$C,B82,'[1]Consolidated Testing(7-10)'!$G:$G,C82,'[1]Consolidated Testing(7-10)'!$J:$J,1) -> 1 | F82: {=[2]Macro_Commentary_Classification!$C$2:$C$46} -> #VALUE!
A83: AIG | B83: Macro factors | C83: In addition to the first quarter share repurchases and dividends that I mentioned earlier, against the backdrop of an unstable macroeconomic environment, we thought it was prudent to raise $750 million of debt at the end of March. | D83: 8 | E83: =COUNTIFS('[1]Consolidated Testing(7-10)'!$C:$C,B83,'[1]Consolidated Testing(7-10)'!$G:$G,C83,'[1]Consolidated Testing(7-10)'!$J:$J,1) -> 1 | F83: {=[2]Macro_Commentary_Classification!$C$2:$C$46} -> #VALUE!
A84: Prudential | B84: Macro factors | C84: The Life business typically experiences elevated seasonal mortality in the first quarter, and that's consistent with what we see across the industry. | D84: 15 | E84: =COUNTIFS('[1]Consolidated Testing(7-10)'!$C:$C,B84,'[1]Consolidated Testing(7-10)'!$G:$G,C84,'[1]Consolidated Testing(7-10)'!$J:$J,1) -> 0
A85: Manulife | B85: Macro factors | C85: "Throughout 2022, we delivered solid core earnings and stable growth in adjusted book value per share despite a challenging market and operating environment." | D85: 5 | E85: =COUNTIFS('[1]Consolidated Testing(7-10)'!$C:$C,B85,'[1]Consolidated Testing(7-10)'!$G:$G,C85,'[1]Consolidated Testing(7-10)'!$J:$J,1) -> 0
A86: Manulife | B86: Macro factors | C86: "The insurance experience losses recognized in core earnings reflected the current period impact of the elevated mortality in 2022 due to the Omicron wave of the pandemic as well as the impact of Hurricane Ian on our property and casualty reinsurance business in the third quarter." | D86: 5 | E86: =COUNTIFS('[1]Consolidated Testing(7-10)'!$C:$C,B86,'[1]Consolidated Testing(7-10)'!$G:$G,C86,'[1]Consolidated Testing(7-10)'!$J:$J,1) -> 0
A87: Metlife | B87: Macro factors | C87: "Taking a broader view of investments rising interest rates are a long-term positive for MetLife." | D87: 5 | E87: =COUNTIFS('[1]Consolidated Testing(7-10)'!$C:$C,B87,'[1]Consolidated Testing(7-10)'!$G:$G,C87,'[1]Consolidated Testing(7-10)'!$J:$J,1) -> 1 | F87: {=[2]Macro_Commentary_Classification!$C$2:$C$46} -> #VALUE!
A88: Manulife | B88: Macro factors | C88: "For the 2022 comparative results, we introduced the transitional net income metric that reflects the impact of hedge accounting and ECL principles as if the standards had allowed such principles to be implemented for 2022." | D88: 6 | E88: =COUNTIFS('[1]Consolidated Testing(7-10)'!$C:$C,B88,'[1]Consolidated Testing(7-10)'!$G:$G,C88,'[1]Consolidated Testing(7-10)'!$J:$J,1) -> 0
A89: Metlife | B89: Macro factors | C89: "Our investment process has stood the test of time, successfully guiding us through the global financial crisis." | D89: 5 | E89: =COUNTIFS('[1]Consolidated Testing(7-10)'!$C:$C,B89,'[1]Consolidated Testing(7-10)'!$G:$G,C89,'[1]Consolidated Testing(7-10)'!$J:$J,1) -> 1 | F89: {=[2]Macro_Commentary_Classification!$C$2:$C$46} -> #VALUE!
A90: Metlife | B90: Macro factors | C90: "Lower interest rates in the quarter drove an MRB loss. This loss was partially offset by derivative gains relating to lower interest rates." | D90: 6 | E90: =COUNTIFS('[1]Consolidated Testing(7-10)'!$C:$C,B90,'[1]Consolidated Testing(7-10)'!$G:$G,C90,'[1]Consolidated Testing(7-10)'!$J:$J,1) -> 1 | F90: {=[2]Macro_Commentary_Classification!$C$2:$C$46} -> #VALUE!
A91: Manulife | B91: Macro factors | C91: "The movements in OCI on insurance contract liabilities and invested assets reflect the impact of interest rates and credit spreads, realized gains or losses from the sale of fair value through OCI fixed income assets, changes in certain insurance contract liabilities due to public equity performance and offsetting changes from ECL recognized in transitional net income." | D91: 6 | E91: =COUNTIFS('[1]Consolidated Testing(7-10)'!$C:$C,B91,'[1]Consolidated Testing(7-10)'!$G:$G,C91,'[1]Consolidated Testing(7-10)'!$J:$J,1) -> 0
A92: Manulife | B92: Macro factors | C92: "The elevated mortality experience from COVID-19 impacted our core earnings in CSM differently in 2022, particularly in our U.S. segment results." | D92: 7 | E92: =COUNTIFS('[1]Consolidated Testing(7-10)'!$C:$C,B92,'[1]Consolidated Testing(7-10)'!$G:$G,C92,'[1]Consolidated Testing(7-10)'!$J:$J,1) -> 0
A93: Metlife | B93: Macro factors | C93: "Overall, the portfolio is well positioned and built for resilience through uncertain markets." | D93: 7 | E93: =COUNTIFS('[1]Consolidated Testing(7-10)'!$C:$C,B93,'[1]Consolidated Testing(7-10)'!$G:$G,C93,'[1]Consolidated Testing(7-10)'!$J:$J,1) -> 1 | F93: {=[2]Macro_Commentary_Classification!$C$2:$C$46} -> #VALUE!
A94: Manulife | B94: Macro factors | C94: Of note, Hong Kong APE sales increased 26% from the prior year quarter, reflecting a return of demand from Mainland Chinese visitors, or MCV, following the border reopening between Hong Kong and Mainland China during the quarter. And our domestic Hong Kong business remained strong with a 21% increase in sales quarter-over-quarter." | D94: 8 | E94: =COUNTIFS('[1]Consolidated Testing(7-10)'!$C:$C,B94,'[1]Consolidated Testing(7-10)'!$G:$G,C94,'[1]Consolidated Testing(7-10)'!$J:$J,1) -> 0
A95: Manulife | B95: Macro factors | C95: "This is illustrated throughout 2022, where the overall change in ECL was a modest $34 million pretax charge despite a backdrop of market volatility and significant equity market declines." | D95: 10 | E95: =COUNTIFS('[1]Consolidated Testing(7-10)'!$C:$C,B95,'[1]Consolidated Testing(7-10)'!$G:$G,C95,'[1]Consolidated Testing(7-10)'!$J:$J,1) -> 0
A96: Metlife | B96: Macro factors | C96: "While market fluctuations are expected to continue, MetLife remains in a position of strength given our balance sheet, investment portfolio, free cash flow generation and the diversification of our market-leading businesses." | D96: 8 | E96: =COUNTIFS('[1]Consolidated Testing(7-10)'!$C:$C,B96,'[1]Consolidated Testing(7-10)'!$G:$G,C96,'[1]Consolidated Testing(7-10)'!$J:$J,1) -> 1 | F96: {=[2]Macro_Commentary_Classification!$C$2:$C$46} -> #VALUE!
A97: Manulife | B97: Macro factors | C97: "In Canada, APE sales decreased 19%, driven by lower segregated fund sales, due to the impact of market volatility and variability in the large case group insurance market." | D97: 10 | E97: =COUNTIFS('[1]Consolidated Testing(7-10)'!$C:$C,B97,'[1]Consolidated Testing(7-10)'!$G:$G,C97,'[1]Consolidated Testing(7-10)'!$J:$J,1) -> 0
A98: Manulife | B98: Macro factors | C98: "APE sales in the U.S. decreased 22%, reflecting the adverse impact of higher short-term interest rates and equity market volatility on consumer sentiment." | D98: 10 | E98: =COUNTIFS('[1]Consolidated Testing(7-10)'!$C:$C,B98,'[1]Consolidated Testing(7-10)'!$G:$G,C98,'[1]Consolidated Testing(7-10)'!$J:$J,1) -> 0
A99: Manulife | B99: Macro factors | C99: "In retail, net inflows were $0.8 billion compared with net inflows of $4 billion in the prior year quarter. The decrease reflected lower investor demand and continued market volatility and higher interest rates." | D99: 11 | E99: =COUNTIFS('[1]Consolidated Testing(7-10)'!$C:$C,B99,'[1]Consolidated Testing(7-10)'!$G:$G,C99,'[1]Consolidated Testing(7-10)'!$J:$J,1) -> 0
A100: Manulife | B100: Macro factors | C100: "Overall, Global WAM's average AUMA decreased by 7% compared with the prior year quarter, driven by the unfavorable impact of markets in 2022." | D100: 11 | E100: =COUNTIFS('[1]Consolidated Testing(7-10)'!$C:$C,B100,'[1]Consolidated Testing(7-10)'!$G:$G,C100,'[1]Consolidated Testing(7-10)'!$J:$J,1) -> 0
...
